project/__init__.py
project/script.py
projectauto-1.0.3.dist-info/METADATA
projectauto-1.0.3.dist-info/WHEEL
projectauto-1.0.3.dist-info/entry_points.txt
projectauto-1.0.3.dist-info/top_level.txt
projectauto-1.0.3.dist-info/RECORD
